Metadata-Version: 2.1
Name: logicarbor
Version: 0.1.0
Summary: Python client for Logicarbor API
Home-page: https://api.logicarbor.com/v3.0/documentation.html
Author: logicarbor dev team
Author-email: admin@logicarbor.com
Classifier: Development Status :: 3 - Alpha
Classifier: Intended Audience :: Developers
Classifier: License :: OSI Approved :: MIT License
Classifier: Programming Language :: Python :: 3
Classifier: Programming Language :: Python :: 3.6
Classifier: Programming Language :: Python :: 3.7
Classifier: Programming Language :: Python :: 3.8
Classifier: Programming Language :: Python :: 3.9
